pts_keysight_daq/__init__.py
pts_keysight_daq/keysight_daq.py
pts_keysight_daq-0.0.15.dist-info/LICENSE.txt
pts_keysight_daq-0.0.15.dist-info/METADATA
pts_keysight_daq-0.0.15.dist-info/WHEEL
pts_keysight_daq-0.0.15.dist-info/top_level.txt
pts_keysight_daq-0.0.15.dist-info/RECORD
